fitz/__init__.py
fitz/frontend.py
fitz/tools/__init__.py
fitz/tools/commandline.py
fitz/tools/graphutils.py
fitz/tools/setup_project.py
fitz-0.0.1.dev0.data/scripts/fitz
fitz-0.0.1.dev0.dist-info/DESCRIPTION.rst
fitz-0.0.1.dev0.dist-info/METADATA
fitz-0.0.1.dev0.dist-info/metadata.json
fitz-0.0.1.dev0.dist-info/RECORD
fitz-0.0.1.dev0.dist-info/top_level.txt
fitz-0.0.1.dev0.dist-info/WHEEL
scripts/__init__.py
scripts/textOnsets2long.py
