Metadata-Version: 2.0
Name: fitz
Version: 0.0.1.dev0
Summary: Fitz: Workflow Mangement for analyzing neuroimaging data.
Home-page: http://github.com/kastman/fitz
Author: Erik Kastman
Author-email: erik.kastman@gmail.com
License: BSD (3-clause)
Keywords: neuroimaging,workflows
Platform: UNKNOWN
Classifier: Development Status :: 2 - Pre-Alpha
Classifier: Intended Audience :: Science/Research
Classifier: Programming Language :: Python :: 2.7
Classifier: License :: OSI Approved :: BSD License
Classifier: Operating System :: POSIX
Classifier: Operating System :: Unix
Classifier: Operating System :: MacOS
Requires-Dist: numpy
Requires-Dist: scipy
Requires-Dist: pandas
Requires-Dist: nipype
Requires-Dist: nibabel
